efb_wechat_comwechat_slave/ChatMgr.py
efb_wechat_comwechat_slave/ComWechat.py
efb_wechat_comwechat_slave/CustomTypes.py
efb_wechat_comwechat_slave/MsgDeco.py
efb_wechat_comwechat_slave/MsgProcess.py
efb_wechat_comwechat_slave/Utils.py
efb_wechat_comwechat_slave/__init__.py
efb_wechat_comwechat_slave/__version__.py
efb_wechat_comwechat_slave-1.0.9.dist-info/METADATA
efb_wechat_comwechat_slave-1.0.9.dist-info/WHEEL
efb_wechat_comwechat_slave-1.0.9.dist-info/entry_points.txt
efb_wechat_comwechat_slave-1.0.9.dist-info/top_level.txt
efb_wechat_comwechat_slave-1.0.9.dist-info/RECORD
