Metadata-Version: 2.2
Name: efb-wechat-comwechat-slave
Version: 1.0.9
Summary: EFB Slave for WeChat on ComWeChat
Home-page: https://github.com/0honus0/efb-wechat-comwechat-slave
Author: honus
Author-email: honusmr@gmail.com
Keywords: wechat
Classifier: Development Status :: 4 - Beta
Classifier: Intended Audience :: Developers
Classifier: Topic :: Software Development :: User Interfaces
Classifier: License :: OSI Approved :: MIT License
Classifier: Programming Language :: Python :: 3.7
Classifier: Operating System :: OS Independent
Requires-Python: >=3.7
Requires-Dist: python-comwechatrobot-http
Requires-Dist: ehforwarderbot
Requires-Dist: PyYaml>=5.3
Requires-Dist: cachetools
Requires-Dist: requests
Requires-Dist: qrcode
Requires-Dist: pyzbar
Requires-Dist: python-magic
Requires-Dist: lxml
Requires-Dist: pilk
Requires-Dist: pydub
Requires-Dist: lottie
Requires-Dist: cairosvg
Dynamic: author
Dynamic: author-email
Dynamic: classifier
Dynamic: description
Dynamic: description-content-type
Dynamic: home-page
Dynamic: keywords
Dynamic: requires-dist
Dynamic: requires-python
Dynamic: summary
